sb3_contrib/__init__.py
sb3_contrib/py.typed
sb3_contrib/version.txt
sb3_contrib/ars/__init__.py
sb3_contrib/ars/ars.py
sb3_contrib/ars/policies.py
sb3_contrib/common/__init__.py
sb3_contrib/common/utils.py
sb3_contrib/common/envs/__init__.py
sb3_contrib/common/envs/invalid_actions_env.py
sb3_contrib/common/maskable/__init__.py
sb3_contrib/common/maskable/buffers.py
sb3_contrib/common/maskable/callbacks.py
sb3_contrib/common/maskable/distributions.py
sb3_contrib/common/maskable/evaluation.py
sb3_contrib/common/maskable/policies.py
sb3_contrib/common/maskable/utils.py
sb3_contrib/common/recurrent/__init__.py
sb3_contrib/common/recurrent/buffers.py
sb3_contrib/common/recurrent/policies.py
sb3_contrib/common/recurrent/type_aliases.py
sb3_contrib/common/vec_env/__init__.py
sb3_contrib/common/vec_env/async_eval.py
sb3_contrib/common/wrappers/__init__.py
sb3_contrib/common/wrappers/action_masker.py
sb3_contrib/common/wrappers/time_feature.py
sb3_contrib/ppo_mask/__init__.py
sb3_contrib/ppo_mask/policies.py
sb3_contrib/ppo_mask/ppo_mask.py
sb3_contrib/ppo_recurrent/__init__.py
sb3_contrib/ppo_recurrent/policies.py
sb3_contrib/ppo_recurrent/ppo_recurrent.py
sb3_contrib/qrdqn/__init__.py
sb3_contrib/qrdqn/policies.py
sb3_contrib/qrdqn/qrdqn.py
sb3_contrib/tqc/__init__.py
sb3_contrib/tqc/policies.py
sb3_contrib/tqc/tqc.py
sb3_contrib/trpo/__init__.py
sb3_contrib/trpo/policies.py
sb3_contrib/trpo/trpo.py
vls_sb3_contrib-1.5.1a8.dist-info/licenses/LICENSE
vls_sb3_contrib-1.5.1a8.dist-info/METADATA
vls_sb3_contrib-1.5.1a8.dist-info/WHEEL
vls_sb3_contrib-1.5.1a8.dist-info/top_level.txt
vls_sb3_contrib-1.5.1a8.dist-info/RECORD
