Metadata-Version: 2.4
Name: vls_sb3_contrib
Version: 1.5.1a8
Summary: Contrib package of Stable Baselines3, experimental code.
Home-page: https://github.com/Stable-Baselines-Team/stable-baselines3-contrib
Author: Antonin Raffin
Author-email: antonin.raffin@dlr.de
License: MIT
Keywords: reinforcement-learning-algorithms reinforcement-learning machine-learning gym openai stable baselines toolbox python data-science
Classifier: Programming Language :: Python :: 3
Classifier: Programming Language :: Python :: 3.7
Classifier: Programming Language :: Python :: 3.8
Classifier: Programming Language :: Python :: 3.9
Requires-Python: >=3.7
License-File: LICENSE
Dynamic: author
Dynamic: author-email
Dynamic: classifier
Dynamic: description
Dynamic: description-content-type
Dynamic: home-page
Dynamic: keywords
Dynamic: license
Dynamic: license-file
Dynamic: requires-python
Dynamic: summary
